upload_to_gcs/__init__.py
upload_to_gcs/main.py
upload_to_gcs-1.0.4.dist-info/METADATA
upload_to_gcs-1.0.4.dist-info/WHEEL
upload_to_gcs-1.0.4.dist-info/entry_points.txt
upload_to_gcs-1.0.4.dist-info/top_level.txt
upload_to_gcs-1.0.4.dist-info/RECORD
